moratab/__init__.py
moratab/math.py
moratab/moratab.py
moratab-0.5.2.dist-info/DESCRIPTION.rst
moratab-0.5.2.dist-info/METADATA
moratab-0.5.2.dist-info/RECORD
moratab-0.5.2.dist-info/WHEEL
moratab-0.5.2.dist-info/metadata.json
moratab-0.5.2.dist-info/top_level.txt
